Metadata-Version: 2.1
Name: xontrib-kitty
Version: 0.0.2
Summary: Xonsh hooks for the Kitty terminal emulator
Home-page: https://github.com/scopatz/xontrib-kitty
Author: Anthony Scopatz
Author-email: scopatz@gmail.com
Maintainer: Anthony Scopatz
License: BSD-2-Clause
Platform: Cross Platform
Classifier: Programming Language :: Python :: 3
Requires-Python: >=3.5
